ActixWebZhongwenWendang/README.md
ActixWebZhongwenWendang/__init__.py
ActixWebZhongwenWendang/__main__.py
ActixWebZhongwenWendang/file.epub
ActixWebZhongwenWendang/index.html
ActixWebZhongwenWendang/css/__init__.py
ActixWebZhongwenWendang/css/annotations.css
ActixWebZhongwenWendang/css/main.css
ActixWebZhongwenWendang/css/normalize.css
ActixWebZhongwenWendang/css/popup.css
ActixWebZhongwenWendang/font/__init__.py
ActixWebZhongwenWendang/font/fontello.eot
ActixWebZhongwenWendang/font/fontello.svg
ActixWebZhongwenWendang/font/fontello.ttf
ActixWebZhongwenWendang/font/fontello.woff
ActixWebZhongwenWendang/img/__init__.py
ActixWebZhongwenWendang/img/annotator-glyph-sprite.png
ActixWebZhongwenWendang/img/annotator-icon-sprite.png
ActixWebZhongwenWendang/img/apple-touch-icon.png
ActixWebZhongwenWendang/img/cancelfullscreen.png
ActixWebZhongwenWendang/img/close.png
ActixWebZhongwenWendang/img/fullscreen.png
ActixWebZhongwenWendang/img/loader.gif
ActixWebZhongwenWendang/img/menu-icon.png
ActixWebZhongwenWendang/img/save.png
ActixWebZhongwenWendang/img/saved.png
ActixWebZhongwenWendang/img/settings-s.png
ActixWebZhongwenWendang/img/settings.png
ActixWebZhongwenWendang/img/star.png
ActixWebZhongwenWendang/js/__init__.py
ActixWebZhongwenWendang/js/epub.js
ActixWebZhongwenWendang/js/epub.min.js
ActixWebZhongwenWendang/js/epub.min.map
ActixWebZhongwenWendang/js/hooks.min.js
ActixWebZhongwenWendang/js/hooks.min.map
ActixWebZhongwenWendang/js/reader.js
ActixWebZhongwenWendang/js/reader.js.map
ActixWebZhongwenWendang/js/reader.min.js
ActixWebZhongwenWendang/js/reader.min.map
ActixWebZhongwenWendang/js/hooks/__init__.py
ActixWebZhongwenWendang/js/hooks/extensions/__init__.py
ActixWebZhongwenWendang/js/hooks/extensions/highlight.js
ActixWebZhongwenWendang/js/libs/__init__.py
ActixWebZhongwenWendang/js/libs/jquery.min.js
ActixWebZhongwenWendang/js/libs/localforage.min.js
ActixWebZhongwenWendang/js/libs/screenfull.js
ActixWebZhongwenWendang/js/libs/screenfull.min.js
actix_web_zhongwen_wendang-2024.3.5.0.dist-info/METADATA
actix_web_zhongwen_wendang-2024.3.5.0.dist-info/WHEEL
actix_web_zhongwen_wendang-2024.3.5.0.dist-info/entry_points.txt
actix_web_zhongwen_wendang-2024.3.5.0.dist-info/top_level.txt
actix_web_zhongwen_wendang-2024.3.5.0.dist-info/RECORD
